__init__.py
memg_core-1.0.0.dist-info/licenses/LICENSE
memory_system/__init__.py
memory_system/config.py
memory_system/exceptions.py
memory_system/logging_config.py
memory_system/sync_wrapper.py
memory_system/template_init.py
memory_system/version.py
memory_system/api/__init__.py
memory_system/kuzu_graph/__init__.py
memory_system/kuzu_graph/interface.py
memory_system/models/__init__.py
memory_system/models/api.py
memory_system/models/core.py
memory_system/models/extraction.py
memory_system/models/template_models.py
memory_system/processing/__init__.py
memory_system/processing/conversation_context.py
memory_system/processing/memory_processor.py
memory_system/processing/memory_retriever.py
memory_system/processing/unified_memory_processor.py
memory_system/prompts/conversation_processing/conversation_summarization.md
memory_system/prompts/conversation_processing/insight_extraction.md
memory_system/prompts/memory_extraction/fact_extraction.txt
memory_system/prompts/memory_processing/document_summarization.md
memory_system/prompts/memory_processing/entity_extraction.md
memory_system/prompts/memory_processing/type_classification.md
memory_system/prompts/unified_analysis/content_analysis.md
memory_system/qdrant/__init__.py
memory_system/qdrant/interface.py
memory_system/templates/__init__.py
memory_system/templates/base.py
memory_system/templates/default.py
memory_system/templates/registry.py
memory_system/utils/README_LOCKED.md
memory_system/utils/__init__.py
memory_system/utils/embeddings.py
memory_system/utils/genai.py
memory_system/utils/prompts.py
memory_system/utils/schema_generator.py
memory_system/utils/schemas.py
memory_system/utils/unified_schemas.py
memory_system/validation/__init__.py
memory_system/validation/graph_validator.py
memory_system/validation/pipeline_validator.py
memory_system/validation/schema_validator.py
memory_system/validation/standalone_validator.py
memg_core-1.0.0.dist-info/METADATA
memg_core-1.0.0.dist-info/WHEEL
memg_core-1.0.0.dist-info/top_level.txt
memg_core-1.0.0.dist-info/RECORD
