Metadata-Version: 2.4
Name: memg-core
Version: 1.0.0
Summary: Core memory system library with dual storage (Qdrant + Kuzu) and AI integration
Author-email: Genovo AI <dev@genovo.ai>
License: MIT
Project-URL: Homepage, https://github.com/genovo-ai/memg-core
Project-URL: Repository, https://github.com/genovo-ai/memg-core
Project-URL: Issues, https://github.com/genovo-ai/memg-core/issues
Classifier: Development Status :: 4 - Beta
Classifier: Intended Audience :: Developers
Classifier: License :: OSI Approved :: MIT License
Classifier: Programming Language :: Python :: 3
Classifier: Programming Language :: Python :: 3.10
Classifier: Programming Language :: Python :: 3.11
Classifier: Programming Language :: Python :: 3.12
Requires-Python: >=3.11
License-File: LICENSE
Requires-Dist: qdrant-client>=1.14.0
Requires-Dist: kuzu==0.11.1
Requires-Dist: pydantic<3.0.0,>=2.11.7
Requires-Dist: pydantic-core<3.0.0,>=2.33.0
Requires-Dist: python-dotenv>=1.0.1
Requires-Dist: google-genai>=1.0.0
Requires-Dist: typing-extensions>=4.12.0
Requires-Dist: httpx>=0.28.0
Provides-Extra: dev
Requires-Dist: pre-commit>=4.2.0; extra == "dev"
Requires-Dist: black>=25.1.0; extra == "dev"
Requires-Dist: isort>=6.0.1; extra == "dev"
Requires-Dist: pylint>=3.3.7; extra == "dev"
Requires-Dist: pytest>=8.4.1; extra == "dev"
Requires-Dist: pytest-asyncio>=0.25.0; extra == "dev"
Requires-Dist: pytest-cov>=6.0.0; extra == "dev"
Requires-Dist: mypy>=1.17.0; extra == "dev"
Requires-Dist: bandit>=1.8.6; extra == "dev"
Requires-Dist: ruff>=0.4.0; extra == "dev"
Dynamic: license-file
